vbz_h5py_plugin/__init__.py
vbz_h5py_plugin/lib/libvbz_hdf_plugin.dylib
vbz_h5py_plugin/lib/libvbz_hdf_plugin_aarch64.so
vbz_h5py_plugin/lib/libvbz_hdf_plugin_m1.dylib
vbz_h5py_plugin/lib/libvbz_hdf_plugin_x86_64.so
vbz_h5py_plugin/lib/vbz_hdf_plugin.dll
vbz_h5py_plugin-1.0.1.dist-info/LICENSE.md
vbz_h5py_plugin-1.0.1.dist-info/METADATA
vbz_h5py_plugin-1.0.1.dist-info/WHEEL
vbz_h5py_plugin-1.0.1.dist-info/top_level.txt
vbz_h5py_plugin-1.0.1.dist-info/RECORD
